apiverve_ipblacklistlookup/__init__.py
apiverve_ipblacklistlookup/apiClient.py
apiverve_ipblacklistlookup/exceptions.py
apiverve_ipblacklistlookup/setup.py
apiverve_ipblacklistlookup/setup_dep.py
apiverve_ipblacklistlookup/tests/__init__.py
apiverve_ipblacklistlookup/tests/test_api.py
apiverve_ipblacklistlookup-1.1.5.dist-info/LICENSE
apiverve_ipblacklistlookup-1.1.5.dist-info/METADATA
apiverve_ipblacklistlookup-1.1.5.dist-info/WHEEL
apiverve_ipblacklistlookup-1.1.5.dist-info/top_level.txt
apiverve_ipblacklistlookup-1.1.5.dist-info/RECORD
